triage/__init__.py
triage/cli.py
triage/database_reflection.py
triage/tracking.py
triage/validation_primitives.py
triage/component/__init__.py
triage/component/architect/__init__.py
triage/component/architect/builders.py
triage/component/architect/database_reflection.py
triage/component/architect/entity_date_table_generators.py
triage/component/architect/feature_dictionary_creator.py
triage/component/architect/feature_generators.py
triage/component/architect/feature_group_creator.py
triage/component/architect/feature_group_mixer.py
triage/component/architect/features.py
triage/component/architect/label_generators.py
triage/component/architect/planner.py
triage/component/architect/utils.py
triage/component/architect/validations.py
triage/component/audition/__init__.py
triage/component/audition/distance_from_best.py
triage/component/audition/metric_directionality.py
triage/component/audition/model_group_performance.py
triage/component/audition/plotting.py
triage/component/audition/pre_audition.py
triage/component/audition/regrets.py
triage/component/audition/rules_maker.py
triage/component/audition/selection_rule_grid.py
triage/component/audition/selection_rule_performance.py
triage/component/audition/selection_rules.py
triage/component/audition/thresholding.py
triage/component/audition/utils.py
triage/component/catwalk/__init__.py
triage/component/catwalk/db.py
triage/component/catwalk/evaluation.py
triage/component/catwalk/exceptions.py
triage/component/catwalk/feature_importances.py
triage/component/catwalk/metrics.py
triage/component/catwalk/model_grouping.py
triage/component/catwalk/model_trainers.py
triage/component/catwalk/predictors.py
triage/component/catwalk/protected_groups_generators.py
triage/component/catwalk/storage.py
triage/component/catwalk/subsetters.py
triage/component/catwalk/utils.py
triage/component/catwalk/baselines/__init__.py
triage/component/catwalk/baselines/rankers.py
triage/component/catwalk/baselines/thresholders.py
triage-5.5.5.dist-info/licenses/AUTHORS.rst
triage-5.5.5.dist-info/licenses/LICENSE
triage-5.5.5.dist-info/METADATA
triage-5.5.5.dist-info/WHEEL
triage-5.5.5.dist-info/entry_points.txt
triage-5.5.5.dist-info/top_level.txt
triage-5.5.5.dist-info/RECORD
