Metadata-Version: 2.4
Name: triage
Version: 5.5.5
Summary: Risk modeling and prediction
Home-page: https://dssg.github.io/triage/
Author: Center for Data Science and Public Policy
Author-email: datascifellows@gmail.com
License: MIT License
Project-URL: Documentation, https://dssg.github.io/triage/
Project-URL: Source Code, https://github.com/dssg/triage
Project-URL: Tutorial, https://dssg.github.io/triage/dirtyduck/
Keywords: triage
Classifier: Development Status :: 2 - Pre-Alpha
Classifier: Intended Audience :: Developers
Classifier: License :: OSI Approved :: MIT License
Classifier: Natural Language :: English
Classifier: Programming Language :: Python :: 3
Classifier: Programming Language :: Python :: 3.9
Classifier: Programming Language :: Python :: 3.10
Requires-Python: >=3.8
License-File: LICENSE
License-File: AUTHORS.rst
Requires-Dist: polars==0.18.2
Requires-Dist: pyarrow>=12.0.1
Requires-Dist: numpy==1.26.0
Requires-Dist: pandas==1.5.0
Requires-Dist: alembic==1.7.7
Requires-Dist: SQLAlchemy==1.3.18
Requires-Dist: PyYAML==6.0.2
Requires-Dist: psycopg2-binary==2.9.3
Requires-Dist: boto3==1.22.4
Requires-Dist: click==8.1.3
Requires-Dist: inflection==0.5.1
Requires-Dist: sqlalchemy-postgres-copy==0.5.0
Requires-Dist: retrying==1.3.3
Requires-Dist: Dickens==1.0.1
Requires-Dist: signalled-timeout==1.0.0
Requires-Dist: wrapt==1.14.0
Requires-Dist: argcmdr==0.7.0
Requires-Dist: sqlparse==0.4.4
Requires-Dist: pebble==4.6.3
Requires-Dist: adjustText==0.7.3
Requires-Dist: graphviz==0.20
Requires-Dist: requests==2.31.0
Requires-Dist: coloredlogs==15.0.1
Requires-Dist: verboselogs==1.7
Requires-Dist: s3fs==0.4.2
Requires-Dist: scikit-learn==1.6.1
Requires-Dist: matplotlib==3.5.1
Requires-Dist: matplotlib-inline==0.1.3
Requires-Dist: seaborn==0.11.2
Requires-Dist: ohio==0.5.0
Requires-Dist: aequitas==0.42.0
Requires-Dist: plotly==5.24.0
Requires-Dist: jupyter==1.0.0
Provides-Extra: rq
Requires-Dist: rq==1.4.3; extra == "rq"
Requires-Dist: redis; extra == "rq"
Dynamic: author
Dynamic: author-email
Dynamic: classifier
Dynamic: description
Dynamic: description-content-type
Dynamic: home-page
Dynamic: keywords
Dynamic: license
Dynamic: license-file
Dynamic: project-url
Dynamic: provides-extra
Dynamic: requires-dist
Dynamic: requires-python
Dynamic: summary
